docformatter_toml/__init__.py
docformatter_toml/__main__.py
docformatter_toml-0.1.0.dist-info/entry_points.txt
docformatter_toml-0.1.0.dist-info/WHEEL
docformatter_toml-0.1.0.dist-info/METADATA
docformatter_toml-0.1.0.dist-info/RECORD
