Metadata-Version: 2.1
Name: docformatter-toml
Version: 0.1.0
Summary: 
Author: Pedro Pablo Correa
Author-email: pbcorrea@uc.cl
Requires-Python: >=3.6.9,<4.0.0
Classifier: Programming Language :: Python :: 3
Classifier: Programming Language :: Python :: 3.7
Classifier: Programming Language :: Python :: 3.8
Classifier: Programming Language :: Python :: 3.9
Requires-Dist: docformatter (>=1.4,<2.0)
Requires-Dist: toml (>=0.10.2,<0.11.0)
